cap2/__init__.py
cap2/api.py
cap2/cli.py
cap2/constants.py
cap2/exceptions.py
cap2/sample.py
cap2/setup_logging.py
cap2/utils.py
cap2/capalyzer/__init__.py
cap2/capalyzer/cli.py
cap2/capalyzer/exceptions.py
cap2/capalyzer/parsers.py
cap2/capalyzer/version.py
cap2/capalyzer/pangea/__init__.py
cap2/capalyzer/pangea/api.py
cap2/capalyzer/pangea/cli.py
cap2/capalyzer/pangea/pangea_file_source.py
cap2/capalyzer/pangea/pangea_file_uploader.py
cap2/capalyzer/pangea/parsers.py
cap2/capalyzer/pangea/utils.py
cap2/capalyzer/table_builder/__init__.py
cap2/capalyzer/table_builder/base_module.py
cap2/capalyzer/table_builder/cap_table_builder.py
cap2/capalyzer/table_builder/parsers.py
cap2/capalyzer/table_builder/modules/__init__.py
cap2/capalyzer/table_builder/modules/basic_stats_summary.py
cap2/capalyzer/table_builder/modules/covid_variant_table.py
cap2/capalyzer/table_builder/modules/kraken2_covid_fast_detect.py
cap2/capalyzer/table_builder/modules/kraken2_fast_taxa.py
cap2/capalyzer/table_builder/modules/kraken2_taxa_table.py
cap2/capalyzer/table_builder/modules/tcem_repertoire_table.py
cap2/capalyzer/table_parser/__init__.py
cap2/capalyzer/table_parser/analysis_utils.py
cap2/capalyzer/table_parser/cap_table_parser.py
cap2/extensions/__init__.py
cap2/extensions/cli.py
cap2/extensions/experimental/__init__.py
cap2/extensions/experimental/cli.py
cap2/extensions/experimental/covid/__init__.py
cap2/extensions/experimental/covid/align_to_covid_genome.py
cap2/extensions/experimental/covid/call_covid_variants.py
cap2/extensions/experimental/covid/cli.py
cap2/extensions/experimental/covid/covid_genome_db.py
cap2/extensions/experimental/covid/fast_detect.py
cap2/extensions/experimental/covid/genome_coverage.py
cap2/extensions/experimental/covid/make_covid_consensus_seq.py
cap2/extensions/experimental/covid/make_pileup.py
cap2/extensions/experimental/preclassify/__init__.py
cap2/extensions/experimental/preclassify/cli.py
cap2/extensions/experimental/preclassify/dynamic_pipeline.py
cap2-0.4.1.dist-info/LICENSE
cap2-0.4.1.dist-info/METADATA
cap2-0.4.1.dist-info/WHEEL
cap2-0.4.1.dist-info/entry_points.txt
cap2-0.4.1.dist-info/top_level.txt
cap2-0.4.1.dist-info/RECORD
