Metadata-Version: 2.1
Name: cap2
Version: 0.4.1
Summary: CAP2
Home-page: https://github.com/metasub/cap2
Author: David C. Danko
Author-email: dcdanko@gmail.com
License: UNKNOWN
Platform: UNKNOWN
Classifier: Intended Audience :: Developers
Classifier: License :: OSI Approved :: MIT License
Classifier: Natural Language :: English
Classifier: Programming Language :: Python :: 3
License-File: LICENSE
Requires-Dist: pandas
Requires-Dist: numpy
Requires-Dist: scipy
Requires-Dist: python-daemon
Requires-Dist: luigi (==3.0.0b2)
Requires-Dist: PyYaml (==5.3.1)
Requires-Dist: biopython (==1.76)
Requires-Dist: click (==6.7)
Requires-Dist: Jinja2 (==3.0.0a1)
Requires-Dist: multiqc (==1.8)
Requires-Dist: pangea-api (>=0.9.23)
Requires-Dist: pysam
Requires-Dist: python-louvain
Requires-Dist: gimmebio.seqs
Requires-Dist: bloom-filter
